torgrims/__init__.py
torgrims/helpers.py
torgrims-0.0.14.dist-info/LICENCE
torgrims-0.0.14.dist-info/METADATA
torgrims-0.0.14.dist-info/WHEEL
torgrims-0.0.14.dist-info/top_level.txt
torgrims-0.0.14.dist-info/RECORD
