Metadata-Version: 2.1
Name: torgrims
Version: 0.0.14
Summary: Package for ML
Home-page: https://irisml.eu
Author: Tomas Torgrimsby
Author-email: torgrimsatpypi@gmail.com
License: OSI Approved (new BSD)
Requires-Python: >=3.6
License-File: LICENCE
Requires-Dist: pandas
Requires-Dist: numpy
Requires-Dist: scikit-learn
